elections_lk/__init__.py
elections_lk/constants/YEAR_TO_REGION_TO_SEATS.py
elections_lk/constants/__init__.py
elections_lk/core/Party.py
elections_lk/core/Seats.py
elections_lk/core/Votes.py
elections_lk/core/__init__.py
elections_lk/core/election/__init__.py
elections_lk/core/election/base/Election.py
elections_lk/core/election/base/ElectionBase.py
elections_lk/core/election/base/ElectionGIGData.py
elections_lk/core/election/base/__init__.py
elections_lk/core/election/categories/ElectionCategory.py
elections_lk/core/election/categories/ElectionParliamentary.py
elections_lk/core/election/categories/ElectionPresidential.py
elections_lk/core/election/categories/__init__.py
elections_lk/core/result/PartyToVotes.py
elections_lk/core/result/Result.py
elections_lk/core/result/VoteSummary.py
elections_lk/core/result/__init__.py
elections_lk/validate/Validate.py
elections_lk/validate/__init__.py
utils_future/AnimatedGIF.py
utils_future/__init__.py
elections_lk_nuuuwan-3.0.9.dist-info/LICENSE
elections_lk_nuuuwan-3.0.9.dist-info/METADATA
elections_lk_nuuuwan-3.0.9.dist-info/WHEEL
elections_lk_nuuuwan-3.0.9.dist-info/top_level.txt
elections_lk_nuuuwan-3.0.9.dist-info/RECORD
